{
  "posts": [
    {
      "id": 1,
      "title": "Post One",
      "body": "This is post One"
    },
    {
      "id": 2,
      "title": "Post Two",
      "body": "This is post Two"
    },
    {
      "id": 3,
      "title": "Post Three",
      "body": "This is post Three"
    },
    {
      "title": "Book One",
      "body": "Post 1",
      "id": 4
    },
    {
      "title": "Book One",
      "body": "Book",
      "id": 5
    },
    {
      "title": "Book One",
      "body": "Book",
      "id": 6
    },
    {
      "title": "Book Two",
      "body": "Book Two",
      "id": 7
    }
  ]
}